baram/airflow_manager.py
baram/async_crawler.py
baram/athena_manager.py
baram/conf_manager.py
baram/ec2_manager.py
baram/ecr_manager.py
baram/efs_manager.py
baram/glue_manager.py
baram/iam_manager.py
baram/kms_manager.py
baram/lambda_manager.py
baram/log_manager.py
baram/poetry_manager.py
baram/process_manager.py
baram/quicksight_manager.py
baram/requests_manager.py
baram/s3_manager.py
baram/sagemaker_manager.py
baram/sagemaker_pipeline_manager.py
baram-0.5.0.dist-info/METADATA
baram-0.5.0.dist-info/WHEEL
baram-0.5.0.dist-info/RECORD
