Metadata-Version: 2.1
Name: baram
Version: 0.5.0
Summary: AWS Framework for python
Author: Kwangsik Lee
Author-email: lks21c@gmail.com
Requires-Python: >=3.9,<4.0
Classifier: Programming Language :: Python :: 3
Classifier: Programming Language :: Python :: 3.9
Classifier: Programming Language :: Python :: 3.10
Classifier: Programming Language :: Python :: 3.11
Requires-Dist: aiohttp (>=3.8.1,<4.0.0)
Requires-Dist: avro (>=1.12.0,<2.0.0)
Requires-Dist: awswrangler[modin] (==3.9.1)
Requires-Dist: boto3 (==1.35.35)
Requires-Dist: fire (>=0.4.0,<0.5.0)
Requires-Dist: nest-asyncio (>=1.5.5,<2.0.0)
Requires-Dist: pytest-cov (>=3.0.0,<4.0.0)
Requires-Dist: requests (>=2.28.1,<3.0.0)
Requires-Dist: sagemaker (>=2.232.2,<3.0.0)
Requires-Dist: six (>=1.16.0,<2.0.0)
Requires-Dist: toml (>=0.10.2,<0.11.0)
Requires-Dist: tzlocal (>=5.2,<6.0)
Requires-Dist: ujson (>=5.5.0,<6.0.0)
